<?xml version="1.0" encoding="UTF-8"?>
<metadata xml:lang="en"><Esri><CreaDate>20230616</CreaDate><CreaTime>13322800</CreaTime><ArcGISFormat>1.0</ArcGISFormat><SyncOnce>TRUE</SyncOnce><DataProperties><lineage><Process ToolSource="c:\program files (x86)\arcgis\desktop10.4\ArcToolbox\Toolboxes\Data Management Tools.tbx\DefineProjection" Date="20230616" Time="133228">DefineProjection Grid_PB_SJ_06J6001300 GEOGCS['GCS_WGS_1984',DATUM['D_WGS_1984',SPHEROID['WGS_1984',6378137.0,298.257223563]],PRIMEM['Greenwich',0.0],UNIT['Degree',0.0174532925199433]]</Process><Process ToolSource="c:\program files (x86)\arcgis\desktop10.4\ArcToolbox\Toolboxes\Data Management Tools.tbx\CalculateField" Date="20230620" Time="111103">CalculateField "New Group Layer\Grid_PB_SJ_06J6001300" Label_3 1 VB #</Process><Process ToolSource="c:\program files (x86)\arcgis\desktop10.4\ArcToolbox\Toolboxes\Data Management Tools.tbx\CalculateField" Date="20230621" Time="091810">CalculateField "New Group Layer\Grid_PB_SJ_06J6001300" DV "No Weed" VB #</Process><Process ToolSource="c:\program files (x86)\arcgis\desktop10.4\ArcToolbox\Toolboxes\Data Management Tools.tbx\CalculateField" Date="20230621" Time="092823">CalculateField "New Group Layer\Grid_PB_SJ_06J6001300" DV "No Weed" VB #</Process><Process ToolSource="c:\program files (x86)\arcgis\desktop10.4\ArcToolbox\Toolboxes\Data Management Tools.tbx\CalculateField" Date="20230621" Time="092913">CalculateField "New Group Layer\Grid_PB_SJ_06J6001300" DV "No Weed" VB #</Process><Process ToolSource="c:\program files (x86)\arcgis\desktop10.4\ArcToolbox\Toolboxes\Data Management Tools.tbx\CalculateField" Date="20230621" Time="093021">CalculateField "New Group Layer\Grid_PB_SJ_06J6001300" DV "No Weed" VB #</Process><Process ToolSource="c:\program files (x86)\arcgis\desktop10.4\ArcToolbox\Toolboxes\Data Management Tools.tbx\CalculateField" Date="20230621" Time="093103">CalculateField "New Group Layer\Grid_PB_SJ_06J6001300" DV "No Weed" VB #</Process><Process ToolSource="c:\program files (x86)\arcgis\desktop10.4\ArcToolbox\Toolboxes\Data Management Tools.tbx\CalculateField" Date="20230621" Time="093258">CalculateField "New Group Layer\Grid_PB_SJ_06J6001300" DV "No Weed" VB #</Process><Process ToolSource="c:\program files (x86)\arcgis\desktop10.4\ArcToolbox\Toolboxes\Data Management Tools.tbx\CalculateField" Date="20230621" Time="093413">CalculateField "New Group Layer\Grid_PB_SJ_06J6001300" DV "No Weed" VB #</Process><Process ToolSource="c:\program files (x86)\arcgis\desktop10.4\ArcToolbox\Toolboxes\Data Management Tools.tbx\CalculateField" Date="20230621" Time="093918">CalculateField "New Group Layer\Grid_PB_SJ_06J6001300" DV "No Weed" VB #</Process><Process ToolSource="c:\program files (x86)\arcgis\desktop10.4\ArcToolbox\Toolboxes\Data Management Tools.tbx\CalculateField" Date="20230621" Time="094007">CalculateField "New Group Layer\Grid_PB_SJ_06J6001300" DV "No Weed" VB #</Process><Process ToolSource="c:\program files (x86)\arcgis\desktop10.4\ArcToolbox\Toolboxes\Data Management Tools.tbx\CalculateField" Date="20230621" Time="094151">CalculateField "New Group Layer\Grid_PB_SJ_06J6001300" DV "No Weed" VB #</Process><Process ToolSource="c:\program files (x86)\arcgis\desktop10.4\ArcToolbox\Toolboxes\Data Management Tools.tbx\CalculateField" Date="20230621" Time="094339">CalculateField "New Group Layer\Grid_PB_SJ_06J6001300" DV "No Weed" VB #</Process><Process ToolSource="c:\program files (x86)\arcgis\desktop10.4\ArcToolbox\Toolboxes\Data Management Tools.tbx\CalculateField" Date="20230621" Time="094426">CalculateField "New Group Layer\Grid_PB_SJ_06J6001300" DV "No Weed" VB #</Process><Process ToolSource="c:\program files (x86)\arcgis\desktop10.4\ArcToolbox\Toolboxes\Data Management Tools.tbx\CalculateField" Date="20230621" Time="094844">CalculateField "New Group Layer\Grid_PB_SJ_06J6001300" DV "No Weed" VB #</Process><Process ToolSource="c:\program files (x86)\arcgis\desktop10.4\ArcToolbox\Toolboxes\Data Management Tools.tbx\CalculateField" Date="20230621" Time="095152">CalculateField "New Group Layer\Grid_PB_SJ_06J6001300" DV "No Weed" VB #</Process><Process ToolSource="c:\program files (x86)\arcgis\desktop10.4\ArcToolbox\Toolboxes\Data Management Tools.tbx\CalculateField" Date="20230621" Time="095243">CalculateField "New Group Layer\Grid_PB_SJ_06J6001300" DV "No Weed" VB #</Process><Process ToolSource="c:\program files (x86)\arcgis\desktop10.4\ArcToolbox\Toolboxes\Data Management Tools.tbx\CalculateField" Date="20230621" Time="095334">CalculateField "New Group Layer\Grid_PB_SJ_06J6001300" DV "No Weed" VB #</Process><Process ToolSource="c:\program files (x86)\arcgis\desktop10.4\ArcToolbox\Toolboxes\Data Management Tools.tbx\CalculateField" Date="20230621" Time="095924">CalculateField "New Group Layer\Grid_PB_SJ_06J6001300" DV "No Weed" VB #</Process><Process ToolSource="c:\program files (x86)\arcgis\desktop10.4\ArcToolbox\Toolboxes\Data Management Tools.tbx\CalculateField" Date="20230621" Time="100135">CalculateField "New Group Layer\Grid_PB_SJ_06J6001300" DV "No Weed" VB #</Process><Process ToolSource="c:\program files (x86)\arcgis\desktop10.4\ArcToolbox\Toolboxes\Data Management Tools.tbx\CalculateField" Date="20230621" Time="100251">CalculateField "New Group Layer\Grid_PB_SJ_06J6001300" DV "No Weed" VB #</Process><Process ToolSource="c:\program files (x86)\arcgis\desktop10.4\ArcToolbox\Toolboxes\Data Management Tools.tbx\CalculateField" Date="20230621" Time="100716">CalculateField "New Group Layer\Grid_PB_SJ_06J6001300" DV "No Weed" VB #</Process><Process ToolSource="c:\program files (x86)\arcgis\desktop10.4\ArcToolbox\Toolboxes\Data Management Tools.tbx\CalculateField" Date="20230621" Time="100807">CalculateField "New Group Layer\Grid_PB_SJ_06J6001300" DV "No Weed" VB #</Process><Process ToolSource="c:\program files (x86)\arcgis\desktop10.4\ArcToolbox\Toolboxes\Data Management Tools.tbx\CalculateField" Date="20230621" Time="101303">CalculateField "New Group Layer\Grid_PB_SJ_06J6001300" DV "No Weed" VB #</Process><Process ToolSource="c:\program files (x86)\arcgis\desktop10.4\ArcToolbox\Toolboxes\Data Management Tools.tbx\CalculateField" Date="20230621" Time="104347">CalculateField "New Group Layer\Grid_PB_SJ_06J6001300" DV "No Weed" VB #</Process><Process ToolSource="c:\program files (x86)\arcgis\desktop10.4\ArcToolbox\Toolboxes\Data Management Tools.tbx\CalculateField" Date="20230621" Time="104440">CalculateField "New Group Layer\Grid_PB_SJ_06J6001300" DV "No Weed" VB #</Process><Process ToolSource="c:\program files (x86)\arcgis\desktop10.4\ArcToolbox\Toolboxes\Data Management Tools.tbx\CalculateField" Date="20230621" Time="104746">CalculateField "New Group Layer\Grid_PB_SJ_06J6001300" DV "No Weed" VB #</Process><Process ToolSource="c:\program files (x86)\arcgis\desktop10.4\ArcToolbox\Toolboxes\Data Management Tools.tbx\CalculateField" Date="20230621" Time="104828">CalculateField "New Group Layer\Grid_PB_SJ_06J6001300" DV "No Weed" VB #</Process><Process ToolSource="c:\program files (x86)\arcgis\desktop10.4\ArcToolbox\Toolboxes\Data Management Tools.tbx\CalculateField" Date="20230621" Time="105255">CalculateField "New Group Layer\Grid_PB_SJ_06J6001300" DV "No Weed" VB #</Process><Process ToolSource="c:\program files (x86)\arcgis\desktop10.4\ArcToolbox\Toolboxes\Data Management Tools.tbx\CalculateField" Date="20230621" Time="105348">CalculateField "New Group Layer\Grid_PB_SJ_06J6001300" DV "No Weed" VB #</Process><Process ToolSource="c:\program files (x86)\arcgis\desktop10.4\ArcToolbox\Toolboxes\Data Management Tools.tbx\CalculateField" Date="20230621" Time="105415">CalculateField "New Group Layer\Grid_PB_SJ_06J6001300" DV "No Weed" VB #</Process><Process ToolSource="c:\program files (x86)\arcgis\desktop10.4\ArcToolbox\Toolboxes\Data Management Tools.tbx\CalculateField" Date="20230621" Time="105656">CalculateField "New Group Layer\Grid_PB_SJ_06J6001300" DV "No Weed" VB #</Process><Process ToolSource="c:\program files (x86)\arcgis\desktop10.4\ArcToolbox\Toolboxes\Data Management Tools.tbx\CalculateField" Date="20230621" Time="105934">CalculateField "New Group Layer\Grid_PB_SJ_06J6001300" DV "No Weed" VB #</Process><Process ToolSource="c:\program files (x86)\arcgis\desktop10.4\ArcToolbox\Toolboxes\Data Management Tools.tbx\CalculateField" Date="20230621" Time="105952">CalculateField "New Group Layer\Grid_PB_SJ_06J6001300" DV "No Weed" VB #</Process><Process ToolSource="c:\program files (x86)\arcgis\desktop10.4\ArcToolbox\Toolboxes\Data Management Tools.tbx\CalculateField" Date="20230621" Time="110054">CalculateField "New Group Layer\Grid_PB_SJ_06J6001300" DV "No Weed" VB #</Process><Process ToolSource="c:\program files (x86)\arcgis\desktop10.4\ArcToolbox\Toolboxes\Data Management Tools.tbx\CalculateField" Date="20230621" Time="110357">CalculateField "New Group Layer\Grid_PB_SJ_06J6001300" DV "No Weed" VB #</Process><Process ToolSource="c:\program files (x86)\arcgis\desktop10.4\ArcToolbox\Toolboxes\Data Management Tools.tbx\CalculateField" Date="20230621" Time="110450">CalculateField "New Group Layer\Grid_PB_SJ_06J6001300" DV "No Weed" VB #</Process><Process ToolSource="c:\program files (x86)\arcgis\desktop10.4\ArcToolbox\Toolboxes\Data Management Tools.tbx\CalculateField" Date="20230621" Time="110611">CalculateField "New Group Layer\Grid_PB_SJ_06J6001300" DV "No Weed" VB #</Process><Process ToolSource="c:\program files (x86)\arcgis\desktop10.4\ArcToolbox\Toolboxes\Data Management Tools.tbx\CalculateField" Date="20230621" Time="110742">CalculateField "New Group Layer\Grid_PB_SJ_06J6001300" DV "No Weed" VB #</Process><Process ToolSource="c:\program files (x86)\arcgis\desktop10.4\ArcToolbox\Toolboxes\Data Management Tools.tbx\CalculateField" Date="20230621" Time="110901">CalculateField "New Group Layer\Grid_PB_SJ_06J6001300" DV "No Weed" VB #</Process><Process ToolSource="c:\program files (x86)\arcgis\desktop10.4\ArcToolbox\Toolboxes\Data Management Tools.tbx\CalculateField" Date="20230621" Time="110945">CalculateField "New Group Layer\Grid_PB_SJ_06J6001300" DV "No Weed" VB #</Process><Process ToolSource="c:\program files (x86)\arcgis\desktop10.4\ArcToolbox\Toolboxes\Data Management Tools.tbx\CalculateField" Date="20230621" Time="111013">CalculateField "New Group Layer\Grid_PB_SJ_06J6001300" DV "No Weed" VB #</Process><Process ToolSource="c:\program files (x86)\arcgis\desktop10.4\ArcToolbox\Toolboxes\Data Management Tools.tbx\CalculateField" Date="20230621" Time="111151">CalculateField "New Group Layer\Grid_PB_SJ_06J6001300" DV "No Weed" VB #</Process><Process ToolSource="c:\program files (x86)\arcgis\desktop10.4\ArcToolbox\Toolboxes\Data Management Tools.tbx\CalculateField" Date="20230621" Time="111257">CalculateField "New Group Layer\Grid_PB_SJ_06J6001300" DV "No Weed" VB #</Process><Process ToolSource="c:\program files (x86)\arcgis\desktop10.4\ArcToolbox\Toolboxes\Data Management Tools.tbx\CalculateField" Date="20230621" Time="111512">CalculateField "New Group Layer\Grid_PB_SJ_06J6001300" DV "No Weed" VB #</Process><Process ToolSource="c:\program files (x86)\arcgis\desktop10.4\ArcToolbox\Toolboxes\Data Management Tools.tbx\CalculateField" Date="20230621" Time="111738">CalculateField "New Group Layer\Grid_PB_SJ_06J6001300" DV "No Weed" VB #</Process><Process ToolSource="c:\program files (x86)\arcgis\desktop10.4\ArcToolbox\Toolboxes\Data Management Tools.tbx\CalculateField" Date="20230621" Time="112022">CalculateField "New Group Layer\Grid_PB_SJ_06J6001300" DV "No Weed" VB #</Process><Process ToolSource="c:\program files (x86)\arcgis\desktop10.4\ArcToolbox\Toolboxes\Data Management Tools.tbx\CalculateField" Date="20230621" Time="112033">CalculateField "New Group Layer\Grid_PB_SJ_06J6001300" DV "No Weed" VB #</Process><Process ToolSource="c:\program files (x86)\arcgis\desktop10.4\ArcToolbox\Toolboxes\Data Management Tools.tbx\CalculateField" Date="20230621" Time="112115">CalculateField "New Group Layer\Grid_PB_SJ_06J6001300" DV "No Weed" VB #</Process><Process ToolSource="c:\program files (x86)\arcgis\desktop10.4\ArcToolbox\Toolboxes\Data Management Tools.tbx\CalculateField" Date="20230621" Time="112204">CalculateField "New Group Layer\Grid_PB_SJ_06J6001300" DV "No Weed" VB #</Process><Process ToolSource="c:\program files (x86)\arcgis\desktop10.4\ArcToolbox\Toolboxes\Data Management Tools.tbx\CalculateField" Date="20230621" Time="112238">CalculateField "New Group Layer\Grid_PB_SJ_06J6001300" DV "No Weed" VB #</Process><Process ToolSource="c:\program files (x86)\arcgis\desktop10.4\ArcToolbox\Toolboxes\Data Management Tools.tbx\CalculateField" Date="20230621" Time="112301">CalculateField "New Group Layer\Grid_PB_SJ_06J6001300" DV "No Weed" VB #</Process><Process ToolSource="c:\program files (x86)\arcgis\desktop10.4\ArcToolbox\Toolboxes\Data Management Tools.tbx\CalculateField" Date="20230621" Time="112322">CalculateField "New Group Layer\Grid_PB_SJ_06J6001300" DV "No Weed" VB #</Process><Process ToolSource="c:\program files (x86)\arcgis\desktop10.4\ArcToolbox\Toolboxes\Data Management Tools.tbx\CalculateField" Date="20230621" Time="112417">CalculateField "New Group Layer\Grid_PB_SJ_06J6001300" DV "No Weed" VB #</Process><Process ToolSource="c:\program files (x86)\arcgis\desktop10.4\ArcToolbox\Toolboxes\Data Management Tools.tbx\CalculateField" Date="20230621" Time="112741">CalculateField "New Group Layer\Grid_PB_SJ_06J6001300" DV "No Weed" VB #</Process><Process ToolSource="c:\program files (x86)\arcgis\desktop10.4\ArcToolbox\Toolboxes\Data Management Tools.tbx\CalculateField" Date="20230621" Time="112812">CalculateField "New Group Layer\Grid_PB_SJ_06J6001300" DV "No Weed" VB #</Process><Process ToolSource="c:\program files (x86)\arcgis\desktop10.4\ArcToolbox\Toolboxes\Data Management Tools.tbx\CalculateField" Date="20230621" Time="112819">CalculateField "New Group Layer\Grid_PB_SJ_06J6001300" DV "No Weed" VB #</Process><Process ToolSource="c:\program files (x86)\arcgis\desktop10.4\ArcToolbox\Toolboxes\Data Management Tools.tbx\CalculateField" Date="20230621" Time="113159">CalculateField "New Group Layer\Grid_PB_SJ_06J6001300" DV "No Weed" VB #</Process><Process ToolSource="c:\program files (x86)\arcgis\desktop10.4\ArcToolbox\Toolboxes\Data Management Tools.tbx\CalculateField" Date="20230621" Time="113511">CalculateField "New Group Layer\Grid_PB_SJ_06J6001300" DV "No Weed" VB #</Process><Process ToolSource="c:\program files (x86)\arcgis\desktop10.4\ArcToolbox\Toolboxes\Data Management Tools.tbx\CalculateField" Date="20230621" Time="130302">CalculateField "New Group Layer\Grid_PB_SJ_06J6001300" DV "No Weed" VB #</Process><Process ToolSource="c:\program files (x86)\arcgis\desktop10.4\ArcToolbox\Toolboxes\Data Management Tools.tbx\CalculateField" Date="20230621" Time="131016">CalculateField "New Group Layer\Grid_PB_SJ_06J6001300" DV "No Weed" VB #</Process><Process ToolSource="c:\program files (x86)\arcgis\desktop10.4\ArcToolbox\Toolboxes\Data Management Tools.tbx\CalculateField" Date="20230621" Time="131153">CalculateField "New Group Layer\Grid_PB_SJ_06J6001300" DV "Weed" VB #</Process><Process ToolSource="c:\program files (x86)\arcgis\desktop10.4\ArcToolbox\Toolboxes\Data Management Tools.tbx\CalculateField" Date="20230622" Time="145045">CalculateField "New Group Layer\Grid_PB_SJ_06J6001300" Plot 1 VB #</Process><Process ToolSource="c:\program files (x86)\arcgis\desktop10.4\ArcToolbox\Toolboxes\Data Management Tools.tbx\CalculateField" Date="20230622" Time="145055">CalculateField "New Group Layer\Grid_PB_SJ_06J6001300" Plot 2 VB #</Process><Process ToolSource="c:\program files (x86)\arcgis\desktop10.4\ArcToolbox\Toolboxes\Data Management Tools.tbx\CalculateField" Date="20230622" Time="145103">CalculateField "New Group Layer\Grid_PB_SJ_06J6001300" Plot 3 VB #</Process><Process ToolSource="c:\program files (x86)\arcgis\desktop10.4\ArcToolbox\Toolboxes\Data Management Tools.tbx\CalculateField" Date="20230622" Time="145112">CalculateField "New Group Layer\Grid_PB_SJ_06J6001300" Plot 4 VB #</Process><Process ToolSource="c:\program files (x86)\arcgis\desktop10.4\ArcToolbox\Toolboxes\Data Management Tools.tbx\CalculateField" Date="20230622" Time="145119">CalculateField "New Group Layer\Grid_PB_SJ_06J6001300" Plot 5 VB #</Process></lineage></DataProperties></Esri></metadata>
